uma_auth/openapi.yaml
uma_auth/models/__init__.py
uma_auth/models/budget_estimate_response.py
uma_auth/models/currency.py
uma_auth/models/currency_preference.py
uma_auth/models/error_code.py
uma_auth/models/error_response.py
uma_auth/models/execute_quote_request.py
uma_auth/models/execute_quote_response.py
uma_auth/models/extra_models.py
uma_auth/models/get_balance_response.py
uma_auth/models/get_info_response.py
uma_auth/models/list_transactions_response.py
uma_auth/models/locked_currency_side.py
uma_auth/models/lookup_user_response.py
uma_auth/models/make_invoice_request.py
uma_auth/models/pay_invoice_request.py
uma_auth/models/pay_invoice_response.py
uma_auth/models/pay_keysend_request.py
uma_auth/models/pay_keysend_request_tlv_records_inner.py
uma_auth/models/pay_keysend_response.py
uma_auth/models/pay_to_address_request.py
uma_auth/models/pay_to_address_response.py
uma_auth/models/quote.py
uma_auth/models/transaction.py
uma_auth/models/transaction_fx.py
uma_auth/models/transaction_type.py
uma_auth_api-0.0.11.dist-info/licenses/LICENSE
uma_auth_api-0.0.11.dist-info/METADATA
uma_auth_api-0.0.11.dist-info/WHEEL
uma_auth_api-0.0.11.dist-info/top_level.txt
uma_auth_api-0.0.11.dist-info/RECORD
