Metadata-Version: 2.4
Name: uma-auth-api
Version: 0.0.11
Summary: This API allows you to authenticate with the UMA server to take actions on a user&#39;s wallet. It&#39;s the exposed communication layer between the NWC server and the main UMA server.
Author: Lightspark Group, Inc.
Author-email: info@lightspark.com
License: Apache-2.0
Project-URL: Documentation, https://docs.uma.me/
Project-URL: Source Code, https://github.com/uma-universal-money-address/uma-auth-api/
Keywords: OpenAPI UMA Auth API
Classifier: Operating System :: OS Independent
Classifier: Programming Language :: Python :: 3
Classifier: Programming Language :: Python :: 3.7
License-File: LICENSE
Requires-Dist: fastapi[all]
Dynamic: license-file
